<?xml version="1.0" encoding="utf-8"?>
<BindInfo>
	<BindNode BINDTYPE="op" DISPLAY="bind_op icmp" ID="" IMPL="auto" LATENCY="0" OPTYPE="icmp" PRAGMA="" RTLNAME="icmp_ln26_fu_155_p2" SOURCE="MAC.c:26" VARIABLE="icmp_ln26" MODULE="MAC" LOOP="VITIS_LOOP_26_1" BUNDLEDNAME="" DSP="0" BRAM="0" URAM="0"/>
	<BindNode BINDTYPE="op" DISPLAY="bind_op add" ID="" IMPL="fabric" LATENCY="0" OPTYPE="add" PRAGMA="" RTLNAME="i_1_fu_161_p2" SOURCE="" VARIABLE="i_1" MODULE="MAC" LOOP="VITIS_LOOP_26_1" BUNDLEDNAME="" DSP="0" BRAM="0" URAM="0"/>
	<BindNode BINDTYPE="op" DISPLAY="bind_op icmp" ID="" IMPL="auto" LATENCY="0" OPTYPE="icmp" PRAGMA="" RTLNAME="icmp_ln28_fu_197_p2" SOURCE="MAC.c:28" VARIABLE="icmp_ln28" MODULE="MAC" LOOP="VITIS_LOOP_26_1" BUNDLEDNAME="" DSP="0" BRAM="0" URAM="0"/>
	<BindNode BINDTYPE="op" DISPLAY="bind_op icmp" ID="" IMPL="auto" LATENCY="0" OPTYPE="icmp" PRAGMA="" RTLNAME="icmp_ln28_1_fu_203_p2" SOURCE="MAC.c:28" VARIABLE="icmp_ln28_1" MODULE="MAC" LOOP="VITIS_LOOP_26_1" BUNDLEDNAME="" DSP="0" BRAM="0" URAM="0"/>
	<BindNode BINDTYPE="op" DISPLAY="bind_op or" ID="" IMPL="auto" LATENCY="0" OPTYPE="or" PRAGMA="" RTLNAME="or_ln28_fu_209_p2" SOURCE="MAC.c:28" VARIABLE="or_ln28" MODULE="MAC" LOOP="VITIS_LOOP_26_1" BUNDLEDNAME="" DSP="0" BRAM="0" URAM="0"/>
	<BindNode BINDTYPE="op" DISPLAY="bind_op fcmp" ID="" IMPL="auto" LATENCY="1" OPTYPE="fcmp" PRAGMA="" RTLNAME="fcmp_32ns_32ns_1_2_no_dsp_1_U4" SOURCE="MAC.c:28" VARIABLE="tmp_1" MODULE="MAC" LOOP="VITIS_LOOP_26_1" BUNDLEDNAME="" DSP="0" BRAM="0" URAM="0"/>
	<BindNode BINDTYPE="op" DISPLAY="bind_op and" ID="" IMPL="auto" LATENCY="0" OPTYPE="and" PRAGMA="" RTLNAME="and_ln28_fu_215_p2" SOURCE="MAC.c:28" VARIABLE="and_ln28" MODULE="MAC" LOOP="VITIS_LOOP_26_1" BUNDLEDNAME="" DSP="0" BRAM="0" URAM="0"/>
	<BindNode BINDTYPE="op" DISPLAY="bind_op select" ID="" IMPL="auto_sel" LATENCY="0" OPTYPE="select" PRAGMA="" RTLNAME="select_ln37_fu_221_p3" SOURCE="MAC.c:37" VARIABLE="select_ln37" MODULE="MAC" LOOP="VITIS_LOOP_26_1" BUNDLEDNAME="" DSP="0" BRAM="0" URAM="0"/>
	<BindNode BINDTYPE="op" DISPLAY="bind_op fmul" ID="" IMPL="maxdsp" LATENCY="3" OPTYPE="fmul" PRAGMA="" RTLNAME="fmul_32ns_32ns_32_4_max_dsp_1_U2" SOURCE="MAC.c:37" VARIABLE="mul" MODULE="MAC" LOOP="VITIS_LOOP_26_1" BUNDLEDNAME="" DSP="3" BRAM="0" URAM="0"/>
	<BindNode BINDTYPE="op" DISPLAY="bind_op fmul" ID="" IMPL="maxdsp" LATENCY="3" OPTYPE="fmul" PRAGMA="" RTLNAME="fmul_32ns_32ns_32_4_max_dsp_1_U2" SOURCE="MAC.c:37" VARIABLE="mul2" MODULE="MAC" LOOP="VITIS_LOOP_26_1" BUNDLEDNAME="" DSP="3" BRAM="0" URAM="0"/>
	<BindNode BINDTYPE="op" DISPLAY="bind_op fsub" ID="" IMPL="fulldsp" LATENCY="6" OPTYPE="fsub" PRAGMA="" RTLNAME="faddfsub_32ns_32ns_32_7_full_dsp_1_U1" SOURCE="MAC.c:37" VARIABLE="y_1" MODULE="MAC" LOOP="VITIS_LOOP_26_1" BUNDLEDNAME="" DSP="2" BRAM="0" URAM="0"/>
	<BindNode BINDTYPE="op" DISPLAY="bind_op fmul" ID="" IMPL="maxdsp" LATENCY="3" OPTYPE="fmul" PRAGMA="" RTLNAME="fmul_32ns_32ns_32_4_max_dsp_1_U3" SOURCE="MAC.c:38" VARIABLE="mul4" MODULE="MAC" LOOP="VITIS_LOOP_26_1" BUNDLEDNAME="" DSP="3" BRAM="0" URAM="0"/>
	<BindNode BINDTYPE="op" DISPLAY="bind_op fsub" ID="" IMPL="fulldsp" LATENCY="6" OPTYPE="fsub" PRAGMA="" RTLNAME="faddfsub_32ns_32ns_32_7_full_dsp_1_U1" SOURCE="MAC.c:38" VARIABLE="z_1" MODULE="MAC" LOOP="VITIS_LOOP_26_1" BUNDLEDNAME="" DSP="2" BRAM="0" URAM="0"/>
	<BindNode BINDTYPE="op" DISPLAY="bind_op fmul" ID="" IMPL="maxdsp" LATENCY="3" OPTYPE="fmul" PRAGMA="" RTLNAME="fmul_32ns_32ns_32_4_max_dsp_1_U2" SOURCE="MAC.c:40" VARIABLE="pow_1" MODULE="MAC" LOOP="VITIS_LOOP_26_1" BUNDLEDNAME="" DSP="3" BRAM="0" URAM="0"/>
</BindInfo>
